MANIFEST.in
README.rst
setup.py
csvfaker/__init__.py
csvfaker/__main__.py
csvfaker/csvfaker.py
csvfaker.egg-info/PKG-INFO
csvfaker.egg-info/SOURCES.txt
csvfaker.egg-info/dependency_links.txt
csvfaker.egg-info/entry_points.txt
csvfaker.egg-info/requires.txt
csvfaker.egg-info/top_level.txt